{
	"pratilipiId": 6755373519123345,
	"title": "Test Series Title",
	"titleEn": "Test Series Title English",
	"displayTitle": "Test Series Title",
	"language": "ENGLISH",
	"isSeries": "true",
	"author": {
		"authorId": 6334457649823744,
		"name": "राधिका गर्ग",
		"displayName": "राधिका गर्ग \"radhik\"",
		"fullName": "राधिका गर्ग \"radhik\"",
		"fullNameEn": "radhika gargg \"garg\"",
		"pageUrl": "/user/राधिका-गर्ग-u12zndqv4o",
		"profileImageUrl": "https://1.ptlp.co/author/image?authorId=5032045519568896&version=717fb5d3-2d6f-4aa6-8338-6f19afb6f16f"
	},
	"summary": "किसी से प्यार करना हमारे बस में नहीं पर किसी से दूर जाना हमारे बस में होता है ,पर क्या सच में अपने प्यार से दूर हो जाना और अकेले ज़िन्दगी बिताना संभव है ? ये कहानी एक ऐस ही रिश्ते की है .",
	"pageUrl": "/series/20181204-1-6F4P3IMr2B6Z",
	"pageUrlEn": "/series/test-english-6F4P3IMr2B6Z",
	"coverImageUrl": "https://pratilipi.s.llnwi.net/pratilipi/cover?pratilipiId=5471245869514752&version=2bcdfa24-38fd-4b70-a93a-1d7df87dad1d",
	"slug": "6F4P3IMr2B6Z",
	"state": "INPROGRESS",
	"listingDateMillis": 1543911294000,
	"lastUpdatedDateMillis": 1543920668000,
	"suggestedTags": [
		"सुग्गेस्टेड"
	],
	"tags": [{
			"id": 5956116436484096,
			"name": "सामाजिक",
			"nameEn": "social"
		},
		{
			"id": 6739392575048840,
			"name": "प्रेरक",
			"nameEn": "moral-inspiring"
		}
	],
	"totalParts": 3,
	"readCount": 6657,
	"readingTime": 300000,
	"averageRating": 4.5,
	"reviewCount": 30,
	"ratingCount": 45,
	"hasAccessToUpdate": true,
	"addedToLib": false,
	"series": null,
	"isPartOfSeries": false
}
